{
  "crosswalk_packs": [
    {
      "id": 1,
      "crosswalk": {
        "id": 1,
        "points": [
          [
            992,
            501
          ],
          [
            764,
            505
          ],
          [
            622,
            581
          ],
          [
            866,
            596
          ]
        ]
      },
      "car_wait": [
        {
          "id": 1,
          "points": [
            [
              859,
              600
            ],
            [
              615,
              585
            ],
            [
              498,
              642
            ],
            [
              768,
              661
            ]
          ]
        }
      ],
      "pedes_wait": [
        {
          "id": 1,
          "points": [
            [
              869,
              599
            ],
            [
              995,
              507
            ],
            [
              1009,
              540
            ],
            [
              970,
              583
            ]
          ]
        },
        {
          "id": 2,
          "points": [
            [
              618,
              573
            ],
            [
              754,
              499
            ],
            [
              646,
              512
            ],
            [
              596,
              538
            ]
          ]
        }
      ],
      "traffic_lights": [
        {
          "id": 1,
          "type": "vehicle",
          "lights": {
            "red": {
              "center": [
                689,
                331
              ],
              "radius": 6
            },
            "yellow": {
              "center": [
                691,
                346
              ],
              "radius": 5
            },
            "green": {
              "center": [
                692,
                361
              ],
              "radius": 5
            }
          }
        }
      ]
    },
    {
      "id": 2,
      "crosswalk": {
        "id": 1,
        "points": [
          [
            920,
            727
          ],
          [
            1257,
            610
          ],
          [
            1587,
            1077
          ],
          [
            875,
            1076
          ]
        ]
      },
      "car_wait": [
        {
          "id": 1,
          "points": [
            [
              908,
              738
            ],
            [
              658,
              807
            ],
            [
              609,
              1077
            ],
            [
              867,
              1071
            ]
          ]
        }
      ],
      "pedes_wait": [
        {
          "id": 1,
          "points": [
            [
              920,
              719
            ],
            [
              1253,
              604
            ],
            [
              1134,
              576
            ],
            [
              938,
              645
            ]
          ]
        }
      ],
      "traffic_lights": [
        {
          "id": 1,
          "type": "pedestrian",
          "lights": {
            "red": {
              "center": [
                1186,
                352
              ],
              "radius": 7
            },
            "green": {
              "center": [
                1186,
                375
              ],
              "radius": 7
            }
          }
        }
      ]
    }
  ],
  "detection_blackout": [
    {
      "id": 1,
      "points": [
        [
          5,
          618
        ],
        [
          174,
          556
        ],
        [
          398,
          463
        ],
        [
          548,
          392
        ],
        [
          608,
          337
        ],
        [
          681,
          312
        ],
        [
          823,
          332
        ],
        [
          914,
          344
        ],
        [
          1085,
          353
        ],
        [
          1226,
          351
        ],
        [
          1228,
          267
        ],
        [
          1320,
          284
        ],
        [
          1455,
          285
        ],
        [
          1549,
          297
        ],
        [
          1617,
          314
        ],
        [
          1722,
          332
        ],
        [
          1914,
          364
        ],
        [
          1912,
          1
        ],
        [
          5,
          3
        ]
      ]
    }
  ],
  "road": [],
  "sidewalk": [],
  "deletion_area": [],
  "deletion_line": []
}